d4n13lbc_poetry_demo/__init__.py
d4n13lbc_poetry_demo-0.1.0.dist-info/METADATA
d4n13lbc_poetry_demo-0.1.0.dist-info/WHEEL
d4n13lbc_poetry_demo-0.1.0.dist-info/RECORD
