Metadata-Version: 2.1
Name: d4n13lbc-poetry-demo
Version: 0.1.0
Summary: 
Author: Daniel Barragan
Author-email: dbarragan1331@gmail.com
Requires-Python: >=3.11,<4.0
Classifier: Programming Language :: Python :: 3
Classifier: Programming Language :: Python :: 3.11
Requires-Dist: wakeonlan (==3.0.0)
